Metadata-Version: 1.0
Name: pingdom-python
Version: 0.2.1
Summary: Pingdom Library
Home-page: https://github.com/johncosta/pingdom-python
Author: John Costa
Author-email: john.costa@gmail.com
License: Apache v2.0
Platform: Posix; MacOS X; Windows
Classifier: Development Status :: 3 - Alpha
Classifier: Intended Audience :: Developers
Classifier: Intended Audience :: System Administrators
Classifier: License :: OSI Approved :: Apache Software License
Classifier: Operating System :: OS Independent
Classifier: Topic :: System :: Monitoring
